apb_extra_osgeo_utils/__init__.py
apb_extra_osgeo_utils-1.1.0.dist-info/METADATA
apb_extra_osgeo_utils-1.1.0.dist-info/WHEEL
apb_extra_osgeo_utils-1.1.0.dist-info/top_level.txt
apb_extra_osgeo_utils-1.1.0.dist-info/RECORD
